polymath/__init__.py
polymath/_version.py
polymath/boolean.py
polymath/matrix.py
polymath/matrix3.py
polymath/pair.py
polymath/polynomial.py
polymath/quaternion.py
polymath/qube.py
polymath/scalar.py
polymath/unit.py
polymath/vector.py
polymath/vector3.py
polymath/extensions/__init__.py
polymath/extensions/broadcaster.py
polymath/extensions/indexer.py
polymath/extensions/item_ops.py
polymath/extensions/iterator.py
polymath/extensions/mask_ops.py
polymath/extensions/math_ops.py
polymath/extensions/pickler.py
polymath/extensions/shaper.py
polymath/extensions/shrinker.py
polymath/extensions/tvl.py
polymath/extensions/vector_ops.py
rms_polymath-1.0.0.dist-info/licenses/LICENSE
rms_polymath-1.0.0.dist-info/METADATA
rms_polymath-1.0.0.dist-info/WHEEL
rms_polymath-1.0.0.dist-info/top_level.txt
rms_polymath-1.0.0.dist-info/RECORD
